etc/warp_beacon/warp_beacon.conf
lib/systemd/system/warp_beacon.service
var/warp_beacon/accounts.json
var/warp_beacon/placeholder.gif
var/warp_beacon/proxies.json
warp_beacon/__init__.py
warp_beacon/__version__.py
warp_beacon/warp_beacon.py
warp_beacon/yt_auth.py
warp_beacon/compress/__init__.py
warp_beacon/compress/video.py
warp_beacon/jobs/__init__.py
warp_beacon/jobs/abstract.py
warp_beacon/jobs/download_job.py
warp_beacon/jobs/types.py
warp_beacon/jobs/upload_job.py
warp_beacon/mediainfo/__init__.py
warp_beacon/mediainfo/abstract.py
warp_beacon/mediainfo/audio.py
warp_beacon/mediainfo/silencer.py
warp_beacon/mediainfo/video.py
warp_beacon/scheduler/__init__.py
warp_beacon/scheduler/instagram_human.py
warp_beacon/scheduler/scheduler.py
warp_beacon/scraper/__init__.py
warp_beacon/scraper/abstract.py
warp_beacon/scraper/account_selector.py
warp_beacon/scraper/exceptions.py
warp_beacon/scraper/fail_handler.py
warp_beacon/scraper/link_resolver.py
warp_beacon/scraper/utils.py
warp_beacon/scraper/X/X.py
warp_beacon/scraper/X/__init__.py
warp_beacon/scraper/X/abstract.py
warp_beacon/scraper/X/types.py
warp_beacon/scraper/instagram/__init__.py
warp_beacon/scraper/instagram/captcha.py
warp_beacon/scraper/instagram/instagram.py
warp_beacon/scraper/instagram/wb_instagrapi.py
warp_beacon/scraper/youtube/__init__.py
warp_beacon/scraper/youtube/abstract.py
warp_beacon/scraper/youtube/music.py
warp_beacon/scraper/youtube/shorts.py
warp_beacon/scraper/youtube/youtube.py
warp_beacon/storage/__init__.py
warp_beacon/storage/mongo.py
warp_beacon/telegram/__init__.py
warp_beacon/telegram/bot.py
warp_beacon/telegram/caption_shortener.py
warp_beacon/telegram/custom_handlers.py
warp_beacon/telegram/download_status.py
warp_beacon/telegram/edit_message.py
warp_beacon/telegram/handlers.py
warp_beacon/telegram/placeholder_message.py
warp_beacon/telegram/progress_bar.py
warp_beacon/telegram/progress_file_reader.py
warp_beacon/telegram/types.py
warp_beacon/telegram/utils.py
warp_beacon-2.8.50.dist-info/licenses/LICENSE
warp_beacon-2.8.50.dist-info/METADATA
warp_beacon-2.8.50.dist-info/WHEEL
warp_beacon-2.8.50.dist-info/entry_points.txt
warp_beacon-2.8.50.dist-info/top_level.txt
warp_beacon-2.8.50.dist-info/RECORD
