Metadata-Version: 2.4
Name: warp_beacon
Version: 2.8.50
Summary: Telegram bot for expanding external media links
Home-page: https://github.com/sb0y/warp_beacon
Author: Andrey Bagrintsev
Author-email: "Andrey (Sb0y) Bagrintsev" <andrey@bagrintsev.me>
License:                                  Apache License
Project-URL: Homepage, https://github.com/sb0y/warp_beacon
Project-URL: Issues, https://github.com/sb0y/warp_beacon/issues
Keywords: bot,telegram,instagram,export
Classifier: Development Status :: 5 - Production/Stable
Classifier: Topic :: Sociology
Classifier: Topic :: Communications :: File Sharing
Classifier: Topic :: Internet :: WWW/HTTP
Classifier: Topic :: Internet :: WWW/HTTP :: Dynamic Content
Classifier: Topic :: Scientific/Engineering :: Image Processing
Classifier: Topic :: Multimedia :: Video
Classifier: Topic :: Multimedia
Classifier: License :: OSI Approved :: Apache Software License
Classifier: Operating System :: POSIX :: Linux
Classifier: Programming Language :: Python :: 3.10
Requires-Python: >=3.10
License-File: LICENSE
Requires-Dist: numpy
Requires-Dist: ffmpeg-python
Requires-Dist: uvloop
Requires-Dist: tgcrypto
Requires-Dist: pyrogram
Requires-Dist: pillow-heif
Requires-Dist: pytubefix
Requires-Dist: av==12.3.0
Requires-Dist: urlextract
Requires-Dist: pillow
Requires-Dist: pymongo
Requires-Dist: instagrapi==2.2.1
Requires-Dist: bs4
Requires-Dist: yt_dlp
Requires-Dist: pydub
Requires-Dist: SpeechRecognition
Requires-Dist: playwright
Requires-Dist: fake-useragent
Requires-Dist: pyotp
Dynamic: author
Dynamic: home-page
Dynamic: license-file
